trovoApi/__init__.py
trovoApi/constants.py
trovoApi/trovo.py
trovoApi/types.py
python_trovo-0.1.7.dist-info/LICENSE
python_trovo-0.1.7.dist-info/METADATA
python_trovo-0.1.7.dist-info/WHEEL
python_trovo-0.1.7.dist-info/RECORD
