Metadata-Version: 2.1
Name: python-trovo
Version: 0.1.7
Summary: A Python wrapper for the Trovo API
Home-page: https://codeberg.org/wolfangaukang/python-trovo
License: GPL-3.0-only
Author: P. R. d. O.
Author-email: d.ol.rod@tutanota.com
Requires-Python: >=3.8,<4.0
Classifier: License :: OSI Approved :: GNU General Public License v3 (GPLv3)
Classifier: Programming Language :: Python :: 3
Classifier: Programming Language :: Python :: 3.8
Classifier: Programming Language :: Python :: 3.9
Classifier: Programming Language :: Python :: 3.10
Classifier: Programming Language :: Python :: 3.11
Requires-Dist: requests (>=2.31,<3.0)
Project-URL: Repository, https://codeberg.org/wolfangaukang/python-trovo
